[{
    "isExterior":true,
    "flags":0,
    "mapColor":14,
    "gridX":0,
    "region":"Ashlands Region",
    "gridY":13,
    "name":"0, 13",
    "objects":[{
        "pos":{
          "XRot":0.89531147480011,
          "YPos":106623.0859375,
          "YRot":0.78442162275314,
          "ZRot":0.63930600881577,
          "ZPos":5734.107421875,
          "XPos":-124.89834594727
        },
        "scale":1,
        "refNum":1,
        "refId":"UNKNOWN_GRASS"
      },{
        "pos":{
          "XRot":0.96239686012268,
          "YPos":106752.7578125,
          "YRot":0.60105019807816,
          "ZRot":2.6387193202972,
          "ZPos":5724.2084960938,
          "XPos":68.334114074707
        },
        "scale":1,
        "refNum":2,
        "refId":"UNKNOWN_GRASS"
      },{
        "pos":{
          "XRot":0.95249718427658,
          "YPos":106544.09375,
          "YRot":0.38559055328369,
          "ZRot":2.8427450656891,
          "ZPos":6166.2592773438,
          "XPos":325.45916748047
        },
        "scale":1,
        "refNum":3,
        "refId":"UNKNOWN_GRASS"
      },{
        "pos":{
          "XRot":1.0014830827713,
          "YPos":106834.3046875,
          "YRot":0.30288487672806,
          "ZRot":2.9324855804443,
          "ZPos":5708.408203125,
          "XPos":265.62921142578
        },
        "scale":1,
        "refNum":4,
        "refId":"UNKNOWN_GRASS"
      },{
        "pos":{
          "XRot":0.84072679281235,
          "YPos":113616.1484375,
          "YRot":-0.40763717889786,
          "ZRot":3.7882812023163,
          "ZPos":2933.8615722656,
          "XPos":1507.4718017578
        },
        "scale":1,
        "refNum":5,
        "refId":"UNKNOWN_GRASS"
      },{
        "pos":{
          "XRot":1.0014830827713,
          "YPos":113945.2109375,
          "YRot":-0.75315129756927,
          "ZRot":2.1060283184052,
          "ZPos":2385.8601074219,
          "XPos":1587.9976806641
        },
        "scale":1,
        "refNum":6,
        "refId":"UNKNOWN_GRASS"
      },{
        "pos":{
          "XRot":1.0428857803345,
          "YPos":113677.6484375,
          "YRot":-0.66055870056152,
          "ZRot":2.2448577880859,
          "ZPos":2691.4338378906,
          "XPos":1746.0180664063
        },
        "scale":1,
        "refNum":7,
        "refId":"UNKNOWN_GRASS"
      },{
        "pos":{
          "XRot":1.0913019180298,
          "YPos":113910.5390625,
          "YRot":-0.8074426651001,
          "ZRot":5.012818813324,
          "ZPos":2163.5288085938,
          "XPos":1858.060546875
        },
        "scale":1,
        "refNum":8,
        "refId":"UNKNOWN_GRASS"
      },{
        "pos":{
          "XRot":0.48052901029587,
          "YPos":112532.6171875,
          "YRot":-0.92684859037399,
          "ZRot":1.081489443779,
          "ZPos":1560.2584228516,
          "XPos":3558.7453613281
        },
        "scale":1,
        "refNum":9,
        "refId":"UNKNOWN_GRASS"
      },{
        "pos":{
          "XRot":0.35764765739441,
          "YPos":112973.5625,
          "YRot":-0.89531147480011,
          "ZRot":6.1368775367737,
          "ZPos":1356.7971191406,
          "XPos":3537.7290039063
        },
        "scale":1,
        "refNum":10,
        "refId":"UNKNOWN_GRASS"
      },{
        "pos":{
          "XRot":0.4380290210247,
          "YPos":112639.7578125,
          "YRot":-0.53549438714981,
          "ZRot":2.0874280929565,
          "ZPos":1133.7368164063,
          "XPos":3933.1005859375
        },
        "scale":1,
        "refNum":11,
        "refId":"UNKNOWN_GRASS"
      },{
        "pos":{
          "XRot":0.2151633054018,
          "YPos":112772.6484375,
          "YRot":-0.4380290210247,
          "ZRot":3.6569302082062,
          "ZPos":1102.2218017578,
          "XPos":3893.2321777344
        },
        "scale":1,
        "refNum":12,
        "refId":"UNKNOWN_GRASS"
      },{
        "pos":{
          "XRot":0.35764765739441,
          "YPos":113257.4375,
          "YRot":-0.91902768611908,
          "ZRot":1.5798567533493,
          "ZPos":1182.9543457031,
          "XPos":3579.2770996094
        },
        "scale":1,
        "refNum":13,
        "refId":"UNKNOWN_GRASS"
      },{
        "pos":{
          "XRot":0.30187466740608,
          "YPos":113382.3828125,
          "YRot":-0.71773391962051,
          "ZRot":1.7292326688766,
          "ZPos":1095.8811035156,
          "XPos":3624.0285644531
        },
        "scale":1,
        "refNum":14,
        "refId":"UNKNOWN_GRASS"
      },{
        "pos":{
          "XRot":0.35877066850662,
          "YPos":113052.6328125,
          "YRot":-0.30288487672806,
          "ZRot":5.6450300216675,
          "ZPos":1027.9827880859,
          "XPos":3927.2956542969
        },
        "scale":1,
        "refNum":15,
        "refId":"UNKNOWN_GRASS"
      },{
        "pos":{
          "XRot":0.15485146641731,
          "YPos":113442.46875,
          "YRot":-0.4380290210247,
          "ZRot":0.98887258768082,
          "ZPos":993.59912109375,
          "XPos":3747.8759765625
        },
        "scale":1,
        "refNum":16,
        "refId":"UNKNOWN_GRASS"
      },{
        "pos":{
          "XRot":0.2151633054018,
          "YPos":113638.0390625,
          "YRot":-0.58044332265854,
          "ZRot":2.1825377941132,
          "ZPos":1017.4129638672,
          "XPos":3643.9274902344
        },
        "scale":1,
        "refNum":17,
        "refId":"UNKNOWN_GRASS"
      },{
        "pos":{
          "XRot":0.18534794449806,
          "YPos":114030.7578125,
          "YRot":-0.64350110292435,
          "ZRot":2.4024789333344,
          "ZPos":1004.8539428711,
          "XPos":3541.8386230469
        },
        "scale":1,
        "refNum":18,
        "refId":"UNKNOWN_GRASS"
      },{
        "pos":{
          "XRot":0.18534794449806,
          "YPos":113540.9609375,
          "YRot":-0.18534794449806,
          "ZRot":2.8521409034729,
          "ZPos":928.49658203125,
          "XPos":3885.7241210938
        },
        "scale":1,
        "refNum":19,
        "refId":"UNKNOWN_GRASS"
      },{
        "pos":{
          "XRot":0,
          "YPos":113992.2890625,
          "YRot":-0.062418811023235,
          "ZRot":5.6247038841248,
          "ZPos":878.79797363281,
          "XPos":3891.2319335938
        },
        "scale":1,
        "refNum":20,
        "refId":"UNKNOWN_GRASS"
      },{
        "pos":{
          "XRot":0,
          "YPos":114108.3828125,
          "YRot":-0.41241043806076,
          "ZRot":4.1209735870361,
          "ZPos":962.984375,
          "XPos":3600.0356445313
        },
        "scale":1,
        "refNum":21,
        "refId":"UNKNOWN_GRASS"
      },{
        "pos":{
          "XRot":0.031209405511618,
          "YPos":114388.234375,
          "YRot":-0.48801854252815,
          "ZRot":1.8554064035416,
          "ZPos":1018.6711425781,
          "XPos":3502.6577148438
        },
        "scale":1,
        "refNum":22,
        "refId":"UNKNOWN_GRASS"
      },{
        "pos":{
          "XRot":0,
          "YPos":114051.9296875,
          "YRot":-0.24497866630554,
          "ZRot":5.6479063034058,
          "ZPos":887.50701904297,
          "XPos":3817.9719238281
        },
        "scale":1,
        "refNum":23,
        "refId":"UNKNOWN_GRASS"
      },{
        "pos":{
          "XRot":-0.062418811023235,
          "YPos":114400.9375,
          "YRot":-0.12435499578714,
          "ZRot":5.1827125549316,
          "ZPos":902.43109130859,
          "XPos":3853.0200195313
        },
        "scale":1,
        "refNum":24,
        "refId":"UNKNOWN_GRASS"
      },{
        "pos":{
          "XRot":1.1309537887573,
          "YPos":111576.90625,
          "YRot":-0.89605540037155,
          "ZRot":4.3188629150391,
          "ZPos":2246.7551269531,
          "XPos":4043.4553222656
        },
        "scale":1,
        "refNum":25,
        "refId":"UNKNOWN_GRASS"
      },{
        "pos":{
          "XRot":1.000967502594,
          "YPos":111750.8984375,
          "YRot":-0.68116557598114,
          "ZRot":3.0283622741699,
          "ZPos":1759.6307373047,
          "XPos":4186.4677734375
        },
        "scale":1,
        "refNum":26,
        "refId":"UNKNOWN_GRASS"
      },{
        "pos":{
          "XRot":1.1193432807922,
          "YPos":111535.2421875,
          "YRot":-0.64350110292435,
          "ZRot":1.634889960289,
          "ZPos":2074.9497070313,
          "XPos":4306.1508789063
        },
        "scale":1,
        "refNum":27,
        "refId":"UNKNOWN_GRASS"
      },{
        "pos":{
          "XRot":0.78442162275314,
          "YPos":111977.765625,
          "YRot":-0.24411641061306,
          "ZRot":1.6276032924652,
          "ZPos":1342.9458007813,
          "XPos":4479.4609375
        },
        "scale":1,
        "refNum":28,
        "refId":"UNKNOWN_GRASS"
      },{
        "pos":{
          "XRot":0.75211405754089,
          "YPos":112002.5546875,
          "YRot":-0.46239995956421,
          "ZRot":5.6024608612061,
          "ZPos":1419.2635498047,
          "XPos":4174.5454101563
        },
        "scale":1,
        "refNum":29,
        "refId":"UNKNOWN_GRASS"
      },{
        "pos":{
          "XRot":0.55733841657639,
          "YPos":112281.3203125,
          "YRot":-0.46239995956421,
          "ZRot":3.1792724132538,
          "ZPos":1232.2537841797,
          "XPos":4085.7224121094
        },
        "scale":1,
        "refNum":30,
        "refId":"UNKNOWN_GRASS"
      },{
        "pos":{
          "XRot":0.60105019807816,
          "YPos":112007.09375,
          "YRot":-0.12388338148594,
          "ZRot":1.9913595914841,
          "ZPos":1339.0177001953,
          "XPos":4360.8637695313
        },
        "scale":1,
        "refNum":31,
        "refId":"UNKNOWN_GRASS"
      },{
        "pos":{
          "XRot":0.24411641061306,
          "YPos":112402.5546875,
          "YRot":0.062177497893572,
          "ZRot":2.6300904750824,
          "ZPos":1140.2016601563,
          "XPos":4253.2744140625
        },
        "scale":1,
        "refNum":32,
        "refId":"UNKNOWN_GRASS"
      },{
        "pos":{
          "XRot":-0.031209405511618,
          "YPos":114298.78125,
          "YRot":0.031209405511618,
          "ZRot":1.7788968086243,
          "ZPos":882,
          "XPos":4006.1496582031
        },
        "scale":1,
        "refNum":33,
        "refId":"UNKNOWN_GRASS"
      },{
        "pos":{
          "XRot":-0.031209405511618,
          "YPos":114400.5625,
          "YRot":-0.031209405511618,
          "ZRot":4.0948948860168,
          "ZPos":886.91149902344,
          "XPos":4017.4155273438
        },
        "scale":1,
        "refNum":34,
        "refId":"UNKNOWN_GRASS"
      },{
        "pos":{
          "XRot":0.15485146641731,
          "YPos":114198.1796875,
          "YRot":0.15485146641731,
          "ZRot":1.4132229089737,
          "ZPos":927.7041015625,
          "XPos":4397.2084960938
        },
        "scale":1,
        "refNum":35,
        "refId":"UNKNOWN_GRASS"
      },{
        "pos":{
          "XRot":0.062418811023235,
          "YPos":114397.6328125,
          "YRot":0.062418811023235,
          "ZRot":0.36183875799179,
          "ZPos":898.00506591797,
          "XPos":4317.7138671875
        },
        "scale":1,
        "refNum":36,
        "refId":"UNKNOWN_GRASS"
      },{
        "pos":{
          "XRot":1.0103121995926,
          "YPos":111645.5234375,
          "YRot":-0.2739317715168,
          "ZRot":0.41131114959717,
          "ZPos":1748.3911132813,
          "XPos":4523.6264648438
        },
        "scale":1,
        "refNum":37,
        "refId":"UNKNOWN_GRASS"
      },{
        "pos":{
          "XRot":0.68116557598114,
          "YPos":111892.203125,
          "YRot":-0.12388338148594,
          "ZRot":3.4506034851074,
          "ZPos":1379.6586914063,
          "XPos":4723.0229492188
        },
        "scale":1,
        "refNum":38,
        "refId":"UNKNOWN_GRASS"
      },{
        "pos":{
          "XRot":0.99213838577271,
          "YPos":111633.6875,
          "YRot":-0.38559055328369,
          "ZRot":0.8926123380661,
          "ZPos":1656.6481933594,
          "XPos":4858.77734375
        },
        "scale":1,
        "refNum":39,
        "refId":"UNKNOWN_GRASS"
      },{
        "pos":{
          "XRot":0.82992297410965,
          "YPos":111807.8359375,
          "YRot":-0.38559055328369,
          "ZRot":0.55474275350571,
          "ZPos":1439.7252197266,
          "XPos":4796.478515625
        },
        "scale":1,
        "refNum":40,
        "refId":"UNKNOWN_GRASS"
      },{
        "pos":{
          "XRot":0.51112341880798,
          "YPos":112001.2109375,
          "YRot":-0.062177497893572,
          "ZRot":1.6145640611649,
          "ZPos":1316.6405029297,
          "XPos":4516.8212890625
        },
        "scale":1,
        "refNum":41,
        "refId":"UNKNOWN_GRASS"
      },{
        "pos":{
          "XRot":0.031209405511618,
          "YPos":112366.296875,
          "YRot":0.15485146641731,
          "ZRot":5.020872592926,
          "ZPos":1215.8465576172,
          "XPos":4724.5151367188
        },
        "scale":1,
        "refNum":42,
        "refId":"UNKNOWN_GRASS"
      },{
        "pos":{
          "XRot":0.35764765739441,
          "YPos":112121.3125,
          "YRot":-0.18466682732105,
          "ZRot":5.3608512878418,
          "ZPos":1230.8793945313,
          "XPos":4841.6831054688
        },
        "scale":1,
        "refNum":43,
        "refId":"UNKNOWN_GRASS"
      },{
        "pos":{
          "XRot":-0.18466682732105,
          "YPos":112320.4765625,
          "YRot":0.24411641061306,
          "ZRot":1.2952946424484,
          "ZPos":1254.1877441406,
          "XPos":4953.8193359375
        },
        "scale":1,
        "refNum":44,
        "refId":"UNKNOWN_GRASS"
      },{
        "pos":{
          "XRot":0.2739317715168,
          "YPos":114070.8203125,
          "YRot":0.2151633054018,
          "ZRot":1.9808131456375,
          "ZPos":997.31713867188,
          "XPos":4580.0888671875
        },
        "scale":1,
        "refNum":45,
        "refId":"UNKNOWN_GRASS"
      },{
        "pos":{
          "XRot":0.18534794449806,
          "YPos":114507.4453125,
          "YRot":0,
          "ZRot":3.7568337917328,
          "ZPos":891.85400390625,
          "XPos":4580.3623046875
        },
        "scale":1,
        "refNum":46,
        "refId":"UNKNOWN_GRASS"
      },{
        "pos":{
          "XRot":0.33082777261734,
          "YPos":114231.265625,
          "YRot":0.09338690340519,
          "ZRot":2.482248544693,
          "ZPos":986.18322753906,
          "XPos":4814.5258789063
        },
        "scale":1,
        "refNum":47,
        "refId":"UNKNOWN_GRASS"
      },{
        "pos":{
          "XRot":0.33082777261734,
          "YPos":114457.3828125,
          "YRot":0.031209405511618,
          "ZRot":3.2348806858063,
          "ZPos":907.72003173828,
          "XPos":4890.4345703125
        },
        "scale":1,
        "refNum":48,
        "refId":"UNKNOWN_GRASS"
      },{
        "pos":{
          "XRot":0.99213838577271,
          "YPos":111689.796875,
          "YRot":0.2151633054018,
          "ZRot":4.7909603118896,
          "ZPos":1586.2464599609,
          "XPos":5224.2885742188
        },
        "scale":1,
        "refNum":49,
        "refId":"UNKNOWN_GRASS"
      },{
        "pos":{
          "XRot":0.51238948106766,
          "YPos":111946.6875,
          "YRot":0.12435499578714,
          "ZRot":2.2795650959015,
          "ZPos":1288.6826171875,
          "XPos":4997.5546875
        },
        "scale":1,
        "refNum":50,
        "refId":"UNKNOWN_GRASS"
      },{
        "pos":{
          "XRot":0.98279374837875,
          "YPos":111680.2265625,
          "YRot":0.062418811023235,
          "ZRot":4.2814712524414,
          "ZPos":1641.3110351563,
          "XPos":5498.4140625
        },
        "scale":1,
        "refNum":51,
        "refId":"UNKNOWN_GRASS"
      },{
        "pos":{
          "XRot":0.60228735208511,
          "YPos":111958.859375,
          "YRot":0,
          "ZRot":0.95013839006424,
          "ZPos":1342.2841796875,
          "XPos":5447.568359375
        },
        "scale":1,
        "refNum":52,
        "refId":"UNKNOWN_GRASS"
      },{
        "pos":{
          "XRot":0.12435499578714,
          "YPos":112032.046875,
          "YRot":0.12435499578714,
          "ZRot":5.0908622741699,
          "ZPos":1285.5888671875,
          "XPos":5244.7578125
        },
        "scale":1,
        "refNum":53,
        "refId":"UNKNOWN_GRASS"
      },{
        "pos":{
          "XRot":-0.30187466740608,
          "YPos":112493.6015625,
          "YRot":0.12388338148594,
          "ZRot":2.2404472827911,
          "ZPos":1354.3734130859,
          "XPos":5199.5688476563
        },
        "scale":1,
        "refNum":54,
        "refId":"UNKNOWN_GRASS"
      },{
        "pos":{
          "XRot":0.18534794449806,
          "YPos":112051.390625,
          "YRot":0,
          "ZRot":0.80344700813293,
          "ZPos":1304.3642578125,
          "XPos":5466.9365234375
        },
        "scale":1,
        "refNum":55,
        "refId":"UNKNOWN_GRASS"
      },{
        "pos":{
          "XRot":-0.2739317715168,
          "YPos":112503.734375,
          "YRot":0.031209405511618,
          "ZRot":5.7203888893127,
          "ZPos":1362.3511962891,
          "XPos":5294.9467773438
        },
        "scale":1,
        "refNum":56,
        "refId":"UNKNOWN_GRASS"
      },{
        "pos":{
          "XRot":0.41241043806076,
          "YPos":112090.0546875,
          "YRot":0.062418811023235,
          "ZRot":6.1859664916992,
          "ZPos":1304.185546875,
          "XPos":5721.3505859375
        },
        "scale":1,
        "refNum":57,
        "refId":"UNKNOWN_GRASS"
      },{
        "pos":{
          "XRot":-0.21059474349022,
          "YPos":112312.2578125,
          "YRot":-0.091279923915863,
          "ZRot":1.9654729366302,
          "ZPos":1295.9948730469,
          "XPos":5646.3715820313
        },
        "scale":1,
        "refNum":58,
        "refId":"UNKNOWN_GRASS"
      },{
        "pos":{
          "XRot":0.18534794449806,
          "YPos":112250.4765625,
          "YRot":-0.062418811023235,
          "ZRot":1.741504907608,
          "ZPos":1265.3986816406,
          "XPos":5914.1923828125
        },
        "scale":1,
        "refNum":59,
        "refId":"UNKNOWN_GRASS"
      },{
        "pos":{
          "XRot":-0.2151633054018,
          "YPos":112397.328125,
          "YRot":-0.2151633054018,
          "ZRot":5.4703426361084,
          "ZPos":1256.8079833984,
          "XPos":5954.794921875
        },
        "scale":1,
        "refNum":60,
        "refId":"UNKNOWN_GRASS"
      },{
        "pos":{
          "XRot":0.53549438714981,
          "YPos":112018.7421875,
          "YRot":0.031209405511618,
          "ZRot":4.7173266410828,
          "ZPos":1347.6090087891,
          "XPos":6082.423828125
        },
        "scale":1,
        "refNum":61,
        "refId":"UNKNOWN_GRASS"
      },{
        "pos":{
          "XRot":0.2720593214035,
          "YPos":112337.234375,
          "YRot":-0.21361993253231,
          "ZRot":0.38158938288689,
          "ZPos":1218.4624023438,
          "XPos":6146.44921875
        },
        "scale":1,
        "refNum":62,
        "refId":"UNKNOWN_GRASS"
      },{
        "pos":{
          "XRot":0.70057326555252,
          "YPos":112105.640625,
          "YRot":0.031209405511618,
          "ZRot":2.6628801822662,
          "ZPos":1277.564453125,
          "XPos":6462.794921875
        },
        "scale":1,
        "refNum":63,
        "refId":"UNKNOWN_GRASS"
      },{
        "pos":{
          "XRot":0.21361993253231,
          "YPos":112475.4609375,
          "YRot":-0.32869455218315,
          "ZRot":0.11543557792902,
          "ZPos":1140.1143798828,
          "XPos":6329.837890625
        },
        "scale":1,
        "refNum":64,
        "refId":"UNKNOWN_GRASS"
      },{
        "pos":{
          "XRot":0.60105019807816,
          "YPos":114143.5703125,
          "YRot":-0.35764765739441,
          "ZRot":0.8736287355423,
          "ZPos":993.51171875,
          "XPos":6056.8217773438
        },
        "scale":1,
        "refNum":65,
        "refId":"UNKNOWN_GRASS"
      },{
        "pos":{
          "XRot":0.30288487672806,
          "YPos":114465.609375,
          "YRot":-0.18534794449806,
          "ZRot":0.94457751512527,
          "ZPos":847.35498046875,
          "XPos":6016.7578125
        },
        "scale":1,
        "refNum":66,
        "refId":"UNKNOWN_GRASS"
      },{
        "pos":{
          "XRot":0.41120913624763,
          "YPos":114143.609375,
          "YRot":-0.24411641061306,
          "ZRot":1.504114151001,
          "ZPos":911.9267578125,
          "XPos":6347.8383789063
        },
        "scale":1,
        "refNum":67,
        "refId":"UNKNOWN_GRASS"
      },{
        "pos":{
          "XRot":0.2151633054018,
          "YPos":114552.453125,
          "YRot":-0.09338690340519,
          "ZRot":5.4876003265381,
          "ZPos":760.45861816406,
          "XPos":6447.3022460938
        },
        "scale":1,
        "refNum":68,
        "refId":"UNKNOWN_GRASS"
      },{
        "pos":{
          "XRot":0.60105019807816,
          "YPos":112240.4921875,
          "YRot":0,
          "ZRot":2.3161900043488,
          "ZPos":1185.0115966797,
          "XPos":6601.9086914063
        },
        "scale":1,
        "refNum":69,
        "refId":"UNKNOWN_GRASS"
      },{
        "pos":{
          "XRot":0.55733841657639,
          "YPos":112372.921875,
          "YRot":-0.12388338148594,
          "ZRot":2.9988322257996,
          "ZPos":1110.0902099609,
          "XPos":6546.8051757813
        },
        "scale":1,
        "refNum":70,
        "refId":"UNKNOWN_GRASS"
      },{
        "pos":{
          "XRot":0.8005450963974,
          "YPos":112101.5703125,
          "YRot":0.031209405511618,
          "ZRot":2.4966299533844,
          "ZPos":1302.0815429688,
          "XPos":6880.9248046875
        },
        "scale":1,
        "refNum":71,
        "refId":"UNKNOWN_GRASS"
      },{
        "pos":{
          "XRot":0.51238948106766,
          "YPos":112493.125,
          "YRot":-0.062418811023235,
          "ZRot":0.71274757385254,
          "ZPos":1000.4349365234,
          "XPos":6850.916015625
        },
        "scale":1,
        "refNum":72,
        "refId":"UNKNOWN_GRASS"
      },{
        "pos":{
          "XRot":0.35877066850662,
          "YPos":112559.9140625,
          "YRot":-0.18534794449806,
          "ZRot":2.9746713638306,
          "ZPos":985.11889648438,
          "XPos":6735.5375976563
        },
        "scale":1,
        "refNum":73,
        "refId":"UNKNOWN_GRASS"
      },{
        "pos":{
          "XRot":0.09338690340519,
          "YPos":112793.265625,
          "YRot":-0.4380290210247,
          "ZRot":5.704665184021,
          "ZPos":990.55639648438,
          "XPos":6550.5473632813
        },
        "scale":1,
        "refNum":74,
        "refId":"UNKNOWN_GRASS"
      },{
        "pos":{
          "XRot":0.30288487672806,
          "YPos":112719.21875,
          "YRot":-0.062418811023235,
          "ZRot":1.2450551986694,
          "ZPos":899.60894775391,
          "XPos":7002.1630859375
        },
        "scale":1,
        "refNum":75,
        "refId":"UNKNOWN_GRASS"
      },{
        "pos":{
          "XRot":0.12435499578714,
          "YPos":112980.7890625,
          "YRot":-0.062418811023235,
          "ZRot":1.254834651947,
          "ZPos":851.84484863281,
          "XPos":6968.904296875
        },
        "scale":1,
        "refNum":76,
        "refId":"UNKNOWN_GRASS"
      },{
        "pos":{
          "XRot":-0.031209405511618,
          "YPos":113122.8203125,
          "YRot":-0.38559055328369,
          "ZRot":5.82297706604,
          "ZPos":888.98315429688,
          "XPos":6768.0385742188
        },
        "scale":1,
        "refNum":77,
        "refId":"UNKNOWN_GRASS"
      },{
        "pos":{
          "XRot":0,
          "YPos":113535.2265625,
          "YRot":-0.51238948106766,
          "ZRot":5.6818466186523,
          "ZPos":972.86407470703,
          "XPos":6622.4638671875
        },
        "scale":1,
        "refNum":78,
        "refId":"UNKNOWN_GRASS"
      },{
        "pos":{
          "XRot":0,
          "YPos":113242.7421875,
          "YRot":-0.18534794449806,
          "ZRot":1.2203190326691,
          "ZPos":828.97229003906,
          "XPos":7024.1479492188
        },
        "scale":1,
        "refNum":79,
        "refId":"UNKNOWN_GRASS"
      },{
        "pos":{
          "XRot":0,
          "YPos":113533.28125,
          "YRot":-0.30288487672806,
          "ZRot":0.0092041660100222,
          "ZPos":889.87713623047,
          "XPos":6809.9931640625
        },
        "scale":1,
        "refNum":80,
        "refId":"UNKNOWN_GRASS"
      },{
        "pos":{
          "XRot":0.09338690340519,
          "YPos":113736.640625,
          "YRot":-0.33082777261734,
          "ZRot":1.6730488538742,
          "ZPos":931.56573486328,
          "XPos":6670.2778320313
        },
        "scale":1,
        "refNum":81,
        "refId":"UNKNOWN_GRASS"
      },{
        "pos":{
          "XRot":0.2151633054018,
          "YPos":114009.8359375,
          "YRot":-0.2151633054018,
          "ZRot":0.93709915876389,
          "ZPos":865.86743164063,
          "XPos":6737.5375976563
        },
        "scale":1,
        "refNum":82,
        "refId":"UNKNOWN_GRASS"
      },{
        "pos":{
          "XRot":0,
          "YPos":113744.84375,
          "YRot":-0.18534794449806,
          "ZRot":5.1202006340027,
          "ZPos":841.50311279297,
          "XPos":6999.9833984375
        },
        "scale":1,
        "refNum":83,
        "refId":"UNKNOWN_GRASS"
      },{
        "pos":{
          "XRot":0.09338690340519,
          "YPos":113798.90625,
          "YRot":-0.2151633054018,
          "ZRot":2.6467728614807,
          "ZPos":868.28454589844,
          "XPos":6867.4086914063
        },
        "scale":1,
        "refNum":84,
        "refId":"UNKNOWN_GRASS"
      },{
        "pos":{
          "XRot":0.24497866630554,
          "YPos":114235.3203125,
          "YRot":-0.12435499578714,
          "ZRot":4.5192456245422,
          "ZPos":807.96887207031,
          "XPos":6745.6083984375
        },
        "scale":1,
        "refNum":85,
        "refId":"UNKNOWN_GRASS"
      },{
        "pos":{
          "XRot":0.18534794449806,
          "YPos":114494.6875,
          "YRot":-0.062418811023235,
          "ZRot":1.0747780799866,
          "ZPos":757.54418945313,
          "XPos":6667.2309570313
        },
        "scale":1,
        "refNum":86,
        "refId":"UNKNOWN_GRASS"
      },{
        "pos":{
          "XRot":0.24497866630554,
          "YPos":114084.7109375,
          "YRot":-0.12435499578714,
          "ZRot":6.2296862602234,
          "ZPos":828.41369628906,
          "XPos":6883.2685546875
        },
        "scale":1,
        "refNum":87,
        "refId":"UNKNOWN_GRASS"
      },{
        "pos":{
          "XRot":0.15485146641731,
          "YPos":114308.4921875,
          "YRot":-0.09338690340519,
          "ZRot":0.12348922342062,
          "ZPos":766.29656982422,
          "XPos":6998.8891601563
        },
        "scale":1,
        "refNum":88,
        "refId":"UNKNOWN_GRASS"
      },{
        "pos":{
          "XRot":0.33082777261734,
          "YPos":112719.3125,
          "YRot":0.031209405511618,
          "ZRot":5.1984362602234,
          "ZPos":904.08203125,
          "XPos":7277.8745117188
        },
        "scale":1,
        "refNum":89,
        "refId":"UNKNOWN_GRASS"
      },{
        "pos":{
          "XRot":0.2151633054018,
          "YPos":112837.8359375,
          "YRot":-0.031209405511618,
          "ZRot":6.0893225669861,
          "ZPos":864.82006835938,
          "XPos":7163.53515625
        },
        "scale":1,
        "refNum":90,
        "refId":"UNKNOWN_GRASS"
      },{
        "pos":{
          "XRot":0.35877066850662,
          "YPos":112660.0546875,
          "YRot":0.062418811023235,
          "ZRot":4.9146409034729,
          "ZPos":932.48614501953,
          "XPos":7456.1064453125
        },
        "scale":1,
        "refNum":91,
        "refId":"UNKNOWN_GRASS"
      },{
        "pos":{
          "XRot":0.18534794449806,
          "YPos":112923.375,
          "YRot":0.062418811023235,
          "ZRot":4.0256719589233,
          "ZPos":848.53186035156,
          "XPos":7354.634765625
        },
        "scale":1,
        "refNum":92,
        "refId":"UNKNOWN_GRASS"
      },{
        "pos":{
          "XRot":0.031209405511618,
          "YPos":113267.546875,
          "YRot":-0.09338690340519,
          "ZRot":0.45004534721375,
          "ZPos":812.34918212891,
          "XPos":7155.4331054688
        },
        "scale":1,
        "refNum":93,
        "refId":"UNKNOWN_GRASS"
      },{
        "pos":{
          "XRot":-0.031209405511618,
          "YPos":113449.8828125,
          "YRot":-0.15485146641731,
          "ZRot":4.0101399421692,
          "ZPos":827.75244140625,
          "XPos":7046.921875
        },
        "scale":1,
        "refNum":94,
        "refId":"UNKNOWN_GRASS"
      },{
        "pos":{
          "XRot":0.15485146641731,
          "YPos":113095.046875,
          "YRot":0.031209405511618,
          "ZRot":6.2663111686707,
          "ZPos":820.6787109375,
          "XPos":7417.09765625
        },
        "scale":1,
        "refNum":95,
        "refId":"UNKNOWN_GRASS"
      },{
        "pos":{
          "XRot":0.062418811023235,
          "YPos":113315.3359375,
          "YRot":0,
          "ZRot":0.22876186668873,
          "ZPos":791.79150390625,
          "XPos":7513.4052734375
        },
        "scale":1,
        "refNum":96,
        "refId":"UNKNOWN_GRASS"
      },{
        "pos":{
          "XRot":0,
          "YPos":113681.484375,
          "YRot":-0.18534794449806,
          "ZRot":3.1271152496338,
          "ZPos":822.16223144531,
          "XPos":7103.134765625
        },
        "scale":1,
        "refNum":97,
        "refId":"UNKNOWN_GRASS"
      },{
        "pos":{
          "XRot":0.062418811023235,
          "YPos":114023.875,
          "YRot":-0.12435499578714,
          "ZRot":6.2454099655151,
          "ZPos":790.71130371094,
          "XPos":7206.3720703125
        },
        "scale":1,
        "refNum":98,
        "refId":"UNKNOWN_GRASS"
      },{
        "pos":{
          "XRot":0.031209405511618,
          "YPos":113776.40625,
          "YRot":-0.09338690340519,
          "ZRot":5.1769599914551,
          "ZPos":784.30633544922,
          "XPos":7381.3461914063
        },
        "scale":1,
        "refNum":99,
        "refId":"UNKNOWN_GRASS"
      },{
        "pos":{
          "XRot":0.062418811023235,
          "YPos":113990.7421875,
          "YRot":-0.12435499578714,
          "ZRot":3.0922162532806,
          "ZPos":767.27838134766,
          "XPos":7410.4018554688
        },
        "scale":1,
        "refNum":100,
        "refId":"UNKNOWN_GRASS"
      },{
        "pos":{
          "XRot":0.12435499578714,
          "YPos":114221.0546875,
          "YRot":-0.062418811023235,
          "ZRot":2.1397767066956,
          "ZPos":757.22216796875,
          "XPos":7282.3354492188
        },
        "scale":1,
        "refNum":101,
        "refId":"UNKNOWN_GRASS"
      },{
        "pos":{
          "XRot":0.062418811023235,
          "YPos":114527.375,
          "YRot":0,
          "ZRot":1.2417954206467,
          "ZPos":732.0390625,
          "XPos":7175.34765625
        },
        "scale":1,
        "refNum":102,
        "refId":"UNKNOWN_GRASS"
      },{
        "pos":{
          "XRot":0.09338690340519,
          "YPos":114285.3125,
          "YRot":-0.031209405511618,
          "ZRot":2.8352665901184,
          "ZPos":739.16796875,
          "XPos":7480.458984375
        },
        "scale":1,
        "refNum":103,
        "refId":"UNKNOWN_GRASS"
      },{
        "pos":{
          "XRot":0,
          "YPos":114466.375,
          "YRot":0,
          "ZRot":2.8360335826874,
          "ZPos":730,
          "XPos":7497.3579101563
        },
        "scale":1,
        "refNum":104,
        "refId":"UNKNOWN_GRASS"
      },{
        "pos":{
          "XRot":0.45868498086929,
          "YPos":112004.7109375,
          "YRot":-0.35431313514709,
          "ZRot":4.0820474624634,
          "ZPos":1217.6196289063,
          "XPos":7706.8720703125
        },
        "scale":1,
        "refNum":105,
        "refId":"UNKNOWN_GRASS"
      },{
        "pos":{
          "XRot":0.4380290210247,
          "YPos":112370.46875,
          "YRot":-0.09338690340519,
          "ZRot":2.3953840732574,
          "ZPos":1053.1800537109,
          "XPos":7595.8374023438
        },
        "scale":1,
        "refNum":106,
        "refId":"UNKNOWN_GRASS"
      },{
        "pos":{
          "XRot":0.24411641061306,
          "YPos":112101.46875,
          "YRot":-0.24411641061306,
          "ZRot":4.3685274124146,
          "ZPos":1068.5017089844,
          "XPos":8034.5224609375
        },
        "scale":1,
        "refNum":107,
        "refId":"UNKNOWN_GRASS"
      },{
        "pos":{
          "XRot":0.2739317715168,
          "YPos":112485.5703125,
          "YRot":-0.031209405511618,
          "ZRot":0.88475042581558,
          "ZPos":1000.607421875,
          "XPos":7878.501953125
        },
        "scale":1,
        "refNum":108,
        "refId":"UNKNOWN_GRASS"
      },{
        "pos":{
          "XRot":0.35877066850662,
          "YPos":112561.4140625,
          "YRot":0,
          "ZRot":5.7426323890686,
          "ZPos":975.4697265625,
          "XPos":7635.1118164063
        },
        "scale":1,
        "refNum":109,
        "refId":"UNKNOWN_GRASS"
      },{
        "pos":{
          "XRot":0.24497866630554,
          "YPos":112933.7265625,
          "YRot":0.062418811023235,
          "ZRot":1.7115913629532,
          "ZPos":857.21337890625,
          "XPos":7562.3208007813
        },
        "scale":1,
        "refNum":110,
        "refId":"UNKNOWN_GRASS"
      },{
        "pos":{
          "XRot":0.2739317715168,
          "YPos":112619.0625,
          "YRot":0.031209405511618,
          "ZRot":3.9209747314453,
          "ZPos":966.24340820313,
          "XPos":7920.1440429688
        },
        "scale":1,
        "refNum":111,
        "refId":"UNKNOWN_GRASS"
      },{
        "pos":{
          "XRot":0.15485146641731,
          "YPos":113010.15625,
          "YRot":0.09338690340519,
          "ZRot":1.2277973890305,
          "ZPos":878.55133056641,
          "XPos":7958.5668945313
        },
        "scale":1,
        "refNum":112,
        "refId":"UNKNOWN_GRASS"
      },{
        "pos":{
          "XRot":0.12435499578714,
          "YPos":113222.59375,
          "YRot":0.12435499578714,
          "ZRot":4.315411567688,
          "ZPos":821.41394042969,
          "XPos":7777.9052734375
        },
        "scale":1,
        "refNum":113,
        "refId":"UNKNOWN_GRASS"
      },{
        "pos":{
          "XRot":0.031209405511618,
          "YPos":113472.2109375,
          "YRot":0.031209405511618,
          "ZRot":5.149730682373,
          "ZPos":788.86047363281,
          "XPos":7597.7670898438
        },
        "scale":1,
        "refNum":114,
        "refId":"UNKNOWN_GRASS"
      },{
        "pos":{
          "XRot":0.18534794449806,
          "YPos":113050.8046875,
          "YRot":0.12435499578714,
          "ZRot":1.1468774080276,
          "ZPos":884.27880859375,
          "XPos":8058.4375
        },
        "scale":1,
        "refNum":115,
        "refId":"UNKNOWN_GRASS"
      },{
        "pos":{
          "XRot":0.12435499578714,
          "YPos":113404.4296875,
          "YRot":0.12435499578714,
          "ZRot":1.7800472974777,
          "ZPos":811.79132080078,
          "XPos":7882.7602539063
        },
        "scale":1,
        "refNum":116,
        "refId":"UNKNOWN_GRASS"
      },{
        "pos":{
          "XRot":0.062418811023235,
          "YPos":113650.1875,
          "YRot":0,
          "ZRot":1.3261668682098,
          "ZPos":778.86328125,
          "XPos":7642.5888671875
        },
        "scale":1,
        "refNum":117,
        "refId":"UNKNOWN_GRASS"
      },{
        "pos":{
          "XRot":0.062418811023235,
          "YPos":113899.4921875,
          "YRot":0.062418811023235,
          "ZRot":5.1324729919434,
          "ZPos":768.63513183594,
          "XPos":7765.6547851563
        },
        "scale":1,
        "refNum":118,
        "refId":"UNKNOWN_GRASS"
      },{
        "pos":{
          "XRot":0.062418811023235,
          "YPos":113723.8828125,
          "YRot":0.18534794449806,
          "ZRot":5.1378421783447,
          "ZPos":808.56787109375,
          "XPos":7990.9897460938
        },
        "scale":1,
        "refNum":119,
        "refId":"UNKNOWN_GRASS"
      },{
        "pos":{
          "XRot":0.09338690340519,
          "YPos":113963.2421875,
          "YRot":0.09338690340519,
          "ZRot":4.5915365219116,
          "ZPos":780.14672851563,
          "XPos":7928.83203125
        },
        "scale":1,
        "refNum":120,
        "refId":"UNKNOWN_GRASS"
      },{
        "pos":{
          "XRot":0.09338690340519,
          "YPos":114076.65625,
          "YRot":0.031209405511618,
          "ZRot":0.27612498402596,
          "ZPos":756.02380371094,
          "XPos":7741.037109375
        },
        "scale":1,
        "refNum":121,
        "refId":"UNKNOWN_GRASS"
      },{
        "pos":{
          "XRot":0,
          "YPos":114515.65625,
          "YRot":0,
          "ZRot":3.3240461349487,
          "ZPos":730,
          "XPos":7573.9536132813
        },
        "scale":1,
        "refNum":122,
        "refId":"UNKNOWN_GRASS"
      },{
        "pos":{
          "XRot":0.09338690340519,
          "YPos":114271.984375,
          "YRot":0.09338690340519,
          "ZRot":0.64966070652008,
          "ZPos":742.98937988281,
          "XPos":7831.9072265625
        },
        "scale":1,
        "refNum":123,
        "refId":"UNKNOWN_GRASS"
      },{
        "pos":{
          "XRot":0.062418811023235,
          "YPos":114359.8828125,
          "YRot":0.062418811023235,
          "ZRot":0.92578566074371,
          "ZPos":740.19451904297,
          "XPos":7898.9951171875
        },
        "scale":1,
        "refNum":124,
        "refId":"UNKNOWN_GRASS"
      }]
  }]